PyAibote/AndroidBot.py
PyAibote/DigitalHumanBot.py
PyAibote/WebBot.py
PyAibote/WindowsBot.py
PyAibote/__init__.py
PyAibote/AndroidBotModel/AndroidHidCorrelation.py
PyAibote/AndroidBotModel/AndroidLoadWait.py
PyAibote/AndroidBotModel/ColorFindingOperation.py
PyAibote/AndroidBotModel/Control.py
PyAibote/AndroidBotModel/CoordinateOperation.py
PyAibote/AndroidBotModel/ElementOperation.py
PyAibote/AndroidBotModel/EquipmentOperation.py
PyAibote/AndroidBotModel/FileTransfer.py
PyAibote/AndroidBotModel/MapFindingOperation.py
PyAibote/AndroidBotModel/OcrCorrelation.py
PyAibote/AndroidBotModel/ScreenProjectionOperation.py
PyAibote/AndroidBotModel/ScreenshotOperation.py
PyAibote/AndroidBotModel/UrlRequest.py
PyAibote/AndroidBotModel/VerificationCodeOperation.py
PyAibote/AndroidBotModel/YoloService.py
PyAibote/AndroidBotModel/__init__.py
PyAibote/CommonUse/ChatGenerative.py
PyAibote/CommonUse/__init__.py
PyAibote/DigitalHumanModel/DigitalHuman.py
PyAibote/DigitalHumanModel/DigitalHumanLoadWait.py
PyAibote/DigitalHumanModel/__init__.py
PyAibote/Tool/DatabaseFunc.py
PyAibote/Tool/DebugStartDriver.py
PyAibote/Tool/GlobalVariable.py
PyAibote/Tool/Logger.py
PyAibote/Tool/LoggerFunc.py
PyAibote/Tool/SendTcpData.py
PyAibote/Tool/SocketServer.py
PyAibote/Tool/Sqlite3DataBase.py
PyAibote/Tool/UniversalFunction.py
PyAibote/Tool/WebsocketsServer.py
PyAibote/Tool/WriteReadFileFunc.py
PyAibote/Tool/__init__.py
PyAibote/WebBotModel/CookiesOperation.py
PyAibote/WebBotModel/DrivingOperation.py
PyAibote/WebBotModel/ElementOperation.py
PyAibote/WebBotModel/IframeOperation.py
PyAibote/WebBotModel/JSinjection.py
PyAibote/WebBotModel/KeymouseOperation.py
PyAibote/WebBotModel/PagesAndNavigation.py
PyAibote/WebBotModel/PopUpWindow.py
PyAibote/WebBotModel/WebLoadWait.py
PyAibote/WebBotModel/WindowOperation.py
PyAibote/WebBotModel/__init__.py
PyAibote/WindowsBotModel/ColorOperation.py
PyAibote/WindowsBotModel/DigitalHumanOperation.py
PyAibote/WindowsBotModel/DrivingOperation.py
pyaibote-2.0.1.dist-info/METADATA
pyaibote-2.0.1.dist-info/WHEEL
pyaibote-2.0.1.dist-info/top_level.txt
pyaibote-2.0.1.dist-info/RECORD
