Metadata-Version: 2.1
Name: pyaibote
Version: 2.0.1
Summary: A pure code RPA office automation framework, which supports Android, Browser and Windows
Home-page: https://www.pyaibote.com
Author: Riven
Author-email: pyaibote@163.com
License: UNKNOWN
Platform: UNKNOWN
Requires-Python: >=3.5,<4.0
Requires-Dist: loguru
Requires-Dist: psutil
Requires-Dist: Pillow
Requires-Dist: requests
Requires-Dist: pymysql
Requires-Dist: websockets
Requires-Dist: asyncio
